{
    "name": "driver_scores_every200_450",
    "longname": "Driver Scores",
    "n_obs": 450,
    "n_dim": 1,
    "time": {
        "index": [
            0,
            1,
            2,
            3,
            4,
            5,
            6,
            7,
            8,
            9,
            10,
            11,
            12,
            13,
            14,
            15,
            16,
            17,
            18,
            19,
            20,
            21,
            22,
            23,
            24,
            25,
            26,
            27,
            28,
            29,
            30,
            31,
            32,
            33,
            34,
            35,
            36,
            37,
            38,
            39,
            40,
            41,
            42,
            43,
            44,
            45,
            46,
            47,
            48,
            49,
            50,
            51,
            52,
            53,
            54,
            55,
            56,
            57,
            58,
            59,
            60,
            61,
            62,
            63,
            64,
            65,
            66,
            67,
            68,
            69,
            70,
            71,
            72,
            73,
            74,
            75,
            76,
            77,
            78,
            79,
            80,
            81,
            82,
            83,
            84,
            85,
            86,
            87,
            88,
            89,
            90,
            91,
            92,
            93,
            94,
            95,
            96,
            97,
            98,
            99,
            100,
            101,
            102,
            103,
            104,
            105,
            106,
            107,
            108,
            109,
            110,
            111,
            112,
            113,
            114,
            115,
            116,
            117,
            118,
            119,
            120,
            121,
            122,
            123,
            124,
            125,
            126,
            127,
            128,
            129,
            130,
            131,
            132,
            133,
            134,
            135,
            136,
            137,
            138,
            139,
            140,
            141,
            142,
            143,
            144,
            145,
            146,
            147,
            148,
            149,
            150,
            151,
            152,
            153,
            154,
            155,
            156,
            157,
            158,
            159,
            160,
            161,
            162,
            163,
            164,
            165,
            166,
            167,
            168,
            169,
            170,
            171,
            172,
            173,
            174,
            175,
            176,
            177,
            178,
            179,
            180,
            181,
            182,
            183,
            184,
            185,
            186,
            187,
            188,
            189,
            190,
            191,
            192,
            193,
            194,
            195,
            196,
            197,
            198,
            199,
            200,
            201,
            202,
            203,
            204,
            205,
            206,
            207,
            208,
            209,
            210,
            211,
            212,
            213,
            214,
            215,
            216,
            217,
            218,
            219,
            220,
            221,
            222,
            223,
            224,
            225,
            226,
            227,
            228,
            229,
            230,
            231,
            232,
            233,
            234,
            235,
            236,
            237,
            238,
            239,
            240,
            241,
            242,
            243,
            244,
            245,
            246,
            247,
            248,
            249,
            250,
            251,
            252,
            253,
            254,
            255,
            256,
            257,
            258,
            259,
            260,
            261,
            262,
            263,
            264,
            265,
            266,
            267,
            268,
            269,
            270,
            271,
            272,
            273,
            274,
            275,
            276,
            277,
            278,
            279,
            280,
            281,
            282,
            283,
            284,
            285,
            286,
            287,
            288,
            289,
            290,
            291,
            292,
            293,
            294,
            295,
            296,
            297,
            298,
            299,
            300,
            301,
            302,
            303,
            304,
            305,
            306,
            307,
            308,
            309,
            310,
            311,
            312,
            313,
            314,
            315,
            316,
            317,
            318,
            319,
            320,
            321,
            322,
            323,
            324,
            325,
            326,
            327,
            328,
            329,
            330,
            331,
            332,
            333,
            334,
            335,
            336,
            337,
            338,
            339,
            340,
            341,
            342,
            343,
            344,
            345,
            346,
            347,
            348,
            349,
            350,
            351,
            352,
            353,
            354,
            355,
            356,
            357,
            358,
            359,
            360,
            361,
            362,
            363,
            364,
            365,
            366,
            367,
            368,
            369,
            370,
            371,
            372,
            373,
            374,
            375,
            376,
            377,
            378,
            379,
            380,
            381,
            382,
            383,
            384,
            385,
            386,
            387,
            388,
            389,
            390,
            391,
            392,
            393,
            394,
            395,
            396,
            397,
            398,
            399,
            400,
            401,
            402,
            403,
            404,
            405,
            406,
            407,
            408,
            409,
            410,
            411,
            412,
            413,
            414,
            415,
            416,
            417,
            418,
            419,
            420,
            421,
            422,
            423,
            424,
            425,
            426,
            427,
            428,
            429,
            430,
            431,
            432,
            433,
            434,
            435,
            436,
            437,
            438,
            439,
            440,
            441,
            442,
            443,
            444,
            445,
            446,
            447,
            448,
            449
        ]
    },
    "series": [
        {
            "label": "Score",
            "type": "float",
            "raw": [
                -0.629724533,
                -1.9754204349,
                0.9126044339,
                0.3555271283,
                -1.9567047555,
                1.0605412585,
                0.4275974405,
                -0.7000292839,
                -1.7526796123,
                1.0149241194,
                -0.3682861002,
                -1.2524392127,
                -0.0441601589,
                -0.7560260573,
                -1.5995308051,
                1.0137919405,
                -0.0447357976,
                0.931007565,
                -1.0535429799,
                1.8297547231,
                -0.7930731128,
                -0.2835354279,
                -0.7183494744,
                -1.1027095838,
                -0.6243503545,
                0.586961142,
                -0.5036848595,
                -1.4348507331,
                0.3426747563,
                1.5764855928,
                -0.2588278968,
                0.4579906683,
                0.7564494195,
                2.0887030016,
                -1.6832640652,
                -0.5675621556,
                1.1353374269,
                -0.0692175853,
                -0.4711690373,
                -1.1591207123,
                -1.4227829855,
                -1.7054904364,
                -1.7449198167,
                -1.8187316722,
                0.0333735703,
                1.1958629962,
                0.2419695215,
                0.883026289,
                -0.9192299795,
                -0.4897124263,
                0.676160403,
                -1.6458926538,
                -1.2153556357,
                0.6732640503,
                -0.855354057,
                2.0304244509,
                -1.3911670893,
                -1.9995612739,
                -1.3822549375,
                -0.6998836358,
                1.4701014174,
                -1.9642364227,
                -0.3231249954,
                -0.7889769552,
                1.4832238897,
                -0.4170466764,
                -0.9524831026,
                -0.6440807528,
                -1.8984029245,
                -0.1499493361,
                -1.2225664167,
                -0.3087684172,
                -1.4667728268,
                -1.9171316013,
                0.9829745491,
                -0.5994742352,
                0.0666160556,
                1.4608747355,
                0.8155479687,
                0.8816647787,
                0.7138369906,
                -1.0065448341,
                -0.1780050789,
                -0.5308903052,
                -1.0014332604,
                0.5589464934,
                0.1195817465,
                -0.1489885533,
                0.6494909813,
                0.8515217995,
                -1.1007884935,
                -0.358571512,
                -1.5278026539,
                -1.3137038156,
                -0.3646459322,
                -1.064894484,
                0.6786954431,
                -0.4528823534,
                1.0012531652,
                -0.4164336217,
                -1.5001233978,
                0.7889749988,
                1.4430031121,
                -0.5190812279,
                1.1159890554,
                -1.5001233978,
                -1.5001233978,
                -1.5001233978,
                -1.1731093412,
                -0.1920671712,
                1.4430031121,
                1.1159890554,
                1.1159890554,
                -0.1920671712,
                -0.1920671712,
                0.1349468854,
                -0.1920671712,
                -0.1920671712,
                0.7889749988,
                -1.5001233978,
                0.1349468854,
                1.1159890554,
                0.7889749988,
                1.1159890554,
                -0.1920671712,
                -0.1920671712,
                -0.1920671712,
                0.1349468854,
                0.4619609421,
                1.1159890554,
                0.4619609421,
                -0.5190812279,
                -0.1920671712,
                1.1159890554,
                1.4430031121,
                -1.5001233978,
                -0.1920671712,
                -0.1920671712,
                1.4430031121,
                0.7889749988,
                1.1159890554,
                1.4430031121,
                1.4430031121,
                1.4430031121,
                -1.5001233978,
                -0.1920671712,
                -0.5190812279,
                0.7889749988,
                -0.1920671712,
                -1.1731093412,
                1.1159890554,
                1.1159890554,
                -1.1731093412,
                -0.1920671712,
                0.1349468854,
                -1.1731093412,
                1.1159890554,
                0.1349468854,
                1.4430031121,
                1.1159890554,
                -1.5001233978,
                1.4430031121,
                1.1159890554,
                -1.5001233978,
                1.1159890554,
                -0.1920671712,
                1.4430031121,
                1.4430031121,
                1.4430031121,
                -0.5190812279,
                0.4619609421,
                -1.5001233978,
                0.7889749988,
                -1.5001233978,
                -0.1920671712,
                0.7889749988,
                1.1159890554,
                -1.5001233978,
                0.4619609421,
                -1.5001233978,
                -1.5001233978,
                -0.5190812279,
                0.4619609421,
                1.4430031121,
                1.4430031121,
                1.1159890554,
                1.1159890554,
                1.1159890554,
                1.4430031121,
                -0.1920671712,
                -0.1920671712,
                -0.5190812279,
                -1.5001233978,
                1.4430031121,
                1.4430031121,
                -1.5001233978,
                1.4430031121,
                1.4430031121,
                1.4430031121,
                0.7889749988,
                -0.2069738219,
                0.1836771172,
                -0.4540524338,
                -0.5865687069,
                -0.7097797108,
                0.2588476415,
                -0.3096356456,
                -0.4284283947,
                -1.0739980365,
                -0.5694150457,
                -0.933163706,
                -0.1146508067,
                -1.0193526366,
                0.1732545393,
                -1.7258510395,
                0.5695208443,
                -0.9628596827,
                0.7092474834,
                0.4147411692,
                3.3145155441,
                -0.8994048707,
                0.2630449444,
                -0.8162573836,
                0.0771305181,
                -1.5706232976,
                0.0862068231,
                -0.9196447212,
                -0.7949886493,
                -0.2025354982,
                -0.0078095935,
                -1.274488591,
                -1.8303315196,
                -0.1192141626,
                -0.0183727065,
                0.3999392673,
                0.2378184416,
                0.2992063384,
                0.4405626535,
                0.8339393127,
                -1.9257042591,
                -0.1675485224,
                -1.2229146379,
                -0.5110029554,
                0.5304721332,
                -1.8153457924,
                0.8509123605,
                0.0905812397,
                -1.2573122279,
                0.3873213618,
                1.5340097412,
                0.5713403911,
                0.6723819736,
                1.1509088191,
                0.4251389061,
                -0.2321214848,
                0.0273585159,
                0.3460851365,
                -1.5674004381,
                -1.0345172592,
                0.5756245231,
                -1.3848225386,
                -0.1003009731,
                -1.7620385788,
                0.6362305419,
                -0.6908130274,
                -0.1688818489,
                -2.0438747398,
                0.1264921222,
                0.9972572217,
                0.0307970551,
                0.6758480342,
                0.4334252276,
                -1.1727230847,
                0.0330399008,
                0.8201623307,
                0.9908092003,
                -1.1153623048,
                0.3528256994,
                -0.3981530486,
                0.070846906,
                1.3912807012,
                -1.3953082537,
                0.7432565659,
                -1.2416527499,
                1.3241042866,
                0.7086176073,
                0.0437921841,
                0.0692683781,
                -0.326395862,
                -0.3635946082,
                -0.4822524535,
                -0.1861855705,
                -0.0189044943,
                0.35900121,
                -0.5468666014,
                0.4516173881,
                0.6104659452,
                -0.5053410034,
                -1.6524812778,
                -0.9399801507,
                1.1159890554,
                -0.1920671712,
                1.4430031121,
                1.1159890554,
                -0.5190812279,
                1.1159890554,
                -0.1920671712,
                0.7889749988,
                -0.1920671712,
                -0.1920671712,
                0.7889749988,
                0.1349468854,
                1.4430031121,
                0.4619609421,
                -1.5001233978,
                -1.5001233978,
                0.1349468854,
                0.4619609421,
                0.7889749988,
                1.1159890554,
                1.1159890554,
                1.1159890554,
                0.1349468854,
                0.4619609421,
                1.4430031121,
                -1.1731093412,
                -0.5190812279,
                1.4430031121,
                0.1349468854,
                -0.1920671712,
                0.7889749988,
                0.7889749988,
                1.1159890554,
                1.1159890554,
                0.1349468854,
                -0.5190812279,
                -1.5001233978,
                1.1159890554,
                -0.1920671712,
                1.1159890554,
                -0.8460952845,
                1.4430031121,
                1.1159890554,
                0.4619609421,
                1.1159890554,
                0.7889749988,
                -0.8460952845,
                -0.1920671712,
                -0.5190812279,
                0.4619609421,
                0.7889749988,
                1.4430031121,
                1.4430031121,
                0.1349468854,
                0.1349468854,
                1.1159890554,
                1.4430031121,
                1.1159890554,
                1.1159890554,
                0.4619609421,
                -1.5001233978,
                1.1159890554,
                -0.8460952845,
                0.7889749988,
                -1.5001233978,
                1.1159890554,
                -0.1920671712,
                -0.5190812279,
                -1.5001233978,
                -1.1731093412,
                -1.1731093412,
                0.4619609421,
                1.1159890554,
                1.1159890554,
                1.4430031121,
                -0.5190812279,
                -0.1920671712,
                1.4430031121,
                1.1159890554,
                -0.5190812279,
                -1.5001233978,
                0.1349468854,
                -0.5190812279,
                1.1159890554,
                1.1159890554,
                1.1159890554,
                -0.1920671712,
                0.1349468854,
                -0.1920671712,
                -0.1920671712,
                0.1349468854,
                1.1159890554,
                -1.5001233978,
                1.4430031121,
                -0.5190812279,
                -1.5001233978,
                -0.1920671712,
                1.4430031121,
                1.4430031121,
                0.1349468854,
                0.4708576998,
                1.017971728,
                -0.7860011918,
                0.3863973866,
                -1.9454906392,
                -0.55435588,
                1.2720630644,
                -0.5524651612,
                -0.1906567458,
                -0.0142059464,
                0.4267807881,
                -0.5076012868,
                0.9139340041,
                0.1382120428,
                -0.9484180908,
                0.9510034097,
                0.4151306628,
                0.4791604681,
                0.7453691492,
                -0.7104925926,
                1.682832688,
                -1.0539282868,
                -0.1564938826,
                0.3319472595,
                -0.8396436998,
                1.8183542838,
                -1.1054317069,
                0.4330735949,
                -0.4047705274,
                -1.0758097035,
                -0.6727762195,
                0.7253851654,
                0.6259009465,
                -0.9243838491,
                -1.8052037862,
                -0.517118074,
                -1.9184341434,
                -0.3016534091,
                -0.1164036354,
                0.0550846563,
                0.1154874228,
                0.4498781853,
                -0.0736888007,
                0.1938853211,
                0.0616010181,
                -1.411597077,
                -1.5754904157,
                -0.2745546466,
                -1.1926415493,
                1.8343565785
            ]
        }
    ]
}